{
  "initTime": 100,
  "result": [
    {
      "search": "Как получить отчет по суммам налогового вычета за 2023 год?",
      "result": [
        "1a9f7664-9362-4f16-9a9d-7242c0cca6d3",
        "03066ad5-b213-420e-9273-f8018a3bc9b0"
      ],
      "time": 10
    },
    {
      "search": "Где найти агрегированный отчет по вкладам по Свердловской области?",
      "result": [
        "442f1a87-3a93-4670-95a7-aed4a857dc0e"
      ],
      "time": 10
    },
    {
      "search": "Какие налоговые льготы доступны пенсионерам?",
      "result": [
        "b22a90c1-4462-4e1f-832b-b6f4e7b99ff3"
      ],
      "time": 8
    },
    {
      "search": "Как получить выписку из ЕГРН онлайн?",
      "result": [
        "c73e4d15-6c47-4972-9c98-8c7e2b1190fc",
        "dbaf3e8f-7801-4c9e-9c82-3a7e2cbe49a9"
      ],
      "time": 9
    },
    {
      "search": "Сроки подачи декларации 3-НДФЛ в 2024 году",
      "result": [
        "ae92c5f4-1244-4d69-a7b4-57fd9be9795d"
      ],
      "time": 7
    }
  ]
}